{
  "headers": {
    "vary": "Accept-Encoding, Origin",
    "etag": "\"54b7a1e1c8f0181f933a7907bc0117c7\"",
    "x-amz-replication-status": "COMPLETED",
    "x-frame-options": "DENY",
    "x-amz-version-id": "qoKESEORrldKNdjyrFHDVggTlS__3MKR",
    "content-length": "1995",
    "accept-ranges": "bytes",
    "cache-control": "public, max-age=31536000, immutable",
    "referrer-policy": "strict-origin-when-cross-origin",
    "server": "deno/gcp-us-east1",
    "strict-transport-security": "max-age=63072000; includeSubDomains; preload",
    "x-amz-cf-pop": "ATL59-P2",
    "content-type": "application/typescript; charset=utf-8",
    "date": "Sun, 18 Jun 2023 20:22:39 GMT",
    "via": "http/2 edgeproxy-h",
    "cross-origin-embedder-policy": "same-origin",
    "x-cache": "Miss from cloudfront",
    "server-timing": "fetchSource;dur=222",
    "x-content-type-options": "nosniff",
    "content-security-policy": "default-src 'none'; style-src 'unsafe-inline'; sandbox",
    "access-control-allow-origin": "*",
    "cross-origin-opener-policy": "same-origin",
    "x-amz-cf-id": "rxeEifDmCs4J2Jnk1cd7_A_t7LOPcax3NROZjcHjlVKYSRXBs9XTig==",
    "cross-origin-resource-policy": "same-origin",
    "last-modified": "Thu, 01 Dec 2022 09:03:03 GMT"
  },
  "url": "https://deno.land/std@0.167.0/encoding/base64url.ts",
  "now": {
    "secs_since_epoch": 1687119758,
    "nanos_since_epoch": 433035392
  }
}